pyarchall/__init__.py
pyarchall/downloader.py
pyarchall/main.py
pyarchall-0.0.2.dist-info/entry_points.txt
pyarchall-0.0.2.dist-info/LICENSE
pyarchall-0.0.2.dist-info/WHEEL
pyarchall-0.0.2.dist-info/METADATA
pyarchall-0.0.2.dist-info/RECORD
