Metadata-Version: 2.1
Name: pyarchall
Version: 0.0.2
Summary: PYthon package to ARCHive ALL versions of single python packge
Author: Alon David
Author-email: alondavid13@gmail.com
Requires-Python: >=3.8,<4.0
Classifier: Programming Language :: Python :: 3
Classifier: Programming Language :: Python :: 3.10
Classifier: Programming Language :: Python :: 3.8
Classifier: Programming Language :: Python :: 3.9
Requires-Dist: BeautifulSoup4
Requires-Dist: aiofiles
Requires-Dist: aiohttp
Requires-Dist: fire
Requires-Dist: requests
Requires-Dist: tqdm
